bboxtools/__init__.py
bboxtools/core/__init__.py
bboxtools/core/bbox.py
bboxtools/core/bbox_parser.py
bboxtools/io/__init__.py
bboxtools/io/api.py
bboxtools/io/reader_coco.py
bboxtools/io/reader_csv.py
bboxtools/io/reader_manifest.py
bboxtools/io/reader_parquet.py
bboxtools/io/reader_pascal_voc.py
bboxtools/io/reader_xml.py
bboxtools/io/reader_yolo.py
bboxtools/io/writer_coco.py
bboxtools/io/writer_json_lines.py
bboxtools/io/writer_pascal_voc.py
bboxtools/io/writer_yolo.py
bboxtools/tests/test_bbox.py
bboxtools/tests/test_to_csv.py
bboxtools/tests/test_to_yolo.py
bboxtools_2-0.0.1.dist-info/LICENSE
bboxtools_2-0.0.1.dist-info/METADATA
bboxtools_2-0.0.1.dist-info/WHEEL
bboxtools_2-0.0.1.dist-info/top_level.txt
bboxtools_2-0.0.1.dist-info/RECORD
