Metadata-Version: 2.1
Name: bboxtools-2
Version: 0.0.1
Summary: Converting bounding box annotations to popular formats like a breeze.
Author-email: Olivier D'Ancona <olivier_dancona@hotmail.com>
Project-URL: repository, https://github.com/ODAncona/bbox-tools.git
Project-URL: documentation, https://github.com/ODAncona/bbox-tools/tree/main/documentation
Keywords: bbox,bounding box,annotation,coco,yolo,voc,object detection
Classifier: Development Status :: 3 - Alpha
Classifier: Intended Audience :: Developers
Classifier: Intended Audience :: Science/Research
Classifier: Topic :: Scientific/Engineering :: Artificial Intelligence
Classifier: License :: OSI Approved :: MIT License
Classifier: Programming Language :: Python :: 3
Classifier: Programming Language :: Python :: 3.7
Classifier: Programming Language :: Python :: 3.8
Classifier: Programming Language :: Python :: 3.9
Classifier: Programming Language :: Python :: 3.10
Classifier: Programming Language :: Python :: 3.11
Requires-Python: >=3.7
License-File: LICENSE
Requires-Dist: pandas
Requires-Dist: xmltodict
